{
  "unversionedId": "Grundlagen/Was ist Informationssicherheit",
  "id": "Grundlagen/Was ist Informationssicherheit",
  "title": "1. Informationssicherheit",
  "description": "| Material   | Video Informationen und Internet              |",
  "source": "@site/docs/Grundlagen/Was ist Informationssicherheit.md",
  "sourceDirName": "Grundlagen",
  "slug": "/Grundlagen/Was ist Informationssicherheit",
  "permalink": "/bbzbl-modul-m231/docs/Grundlagen/Was ist Informationssicherheit",
  "draft": false,
  "editUrl": "https://github.com/codingluke/bbzbl-modul-m231/tree/main/docs/Grundlagen/Was ist Informationssicherheit.md",
  "tags": [],
  "version": "current",
  "sidebarPosition": 1,
  "frontMatter": {
    "sidebar_position": 1
  },
  "sidebar": "tutorialSidebar",
  "previous": {
    "title": "Grundlagen",
    "permalink": "/bbzbl-modul-m231/docs/category/grundlagen"
  },
  "next": {
    "title": "2. Was ist Daten ?",
    "permalink": "/bbzbl-modul-m231/docs/Grundlagen/Was sind Daten"
  }
}